{
  "prefix": "ASPIRE",
  "repo": "aspire",
  "description": "Aspire hosting and configuration diagnostics",
  "generated_at": "2026-02-05T02:04:58.7803623Z",
  "diagnostics": [
    {
      "id": "ASPIRE006",
      "category": "Analyzer",
      "url": "https://raw.githubusercontent.com/microsoft/aspire.dev/main/src/frontend/src/content/docs/diagnostics/aspire006.mdx",
      "error_url": "https://aka.ms/aspire/diagnostics/ASPIRE006"
    },
    {
      "id": "ASPIRE007",
      "category": "Analyzer",
      "url": "https://raw.githubusercontent.com/microsoft/aspire.dev/main/src/frontend/src/content/docs/diagnostics/aspire007.mdx",
      "error_url": "https://aka.ms/aspire/diagnostics/ASPIRE007"
    },
    {
      "id": "ASPIRE008",
      "category": "Analyzer",
      "url": "https://raw.githubusercontent.com/microsoft/aspire.dev/main/src/frontend/src/content/docs/diagnostics/aspire008.mdx",
      "error_url": "https://aka.ms/aspire/diagnostics/ASPIRE008"
    },
    {
      "id": "ASPIRE009",
      "category": "Analyzer",
      "url": "https://raw.githubusercontent.com/microsoft/aspire.dev/main/src/frontend/src/content/docs/diagnostics/aspire009.mdx",
      "error_url": "https://aka.ms/aspire/diagnostics/ASPIRE009"
    },
    {
      "id": "ASPIRE010",
      "category": "Analyzer",
      "url": "https://raw.githubusercontent.com/microsoft/aspire.dev/main/src/frontend/src/content/docs/diagnostics/aspire010.mdx",
      "error_url": "https://aka.ms/aspire/diagnostics/ASPIRE010"
    },
    {
      "id": "ASPIRE011",
      "category": "Analyzer",
      "url": "https://raw.githubusercontent.com/microsoft/aspire.dev/main/src/frontend/src/content/docs/diagnostics/aspire011.mdx",
      "error_url": "https://aka.ms/aspire/diagnostics/ASPIRE011"
    },
    {
      "id": "ASPIRE012",
      "category": "Analyzer",
      "url": "https://raw.githubusercontent.com/microsoft/aspire.dev/main/src/frontend/src/content/docs/diagnostics/aspire012.mdx",
      "error_url": "https://aka.ms/aspire/diagnostics/ASPIRE012"
    },
    {
      "id": "ASPIRE013",
      "category": "Analyzer",
      "url": "https://raw.githubusercontent.com/microsoft/aspire.dev/main/src/frontend/src/content/docs/diagnostics/aspire013.mdx",
      "error_url": "https://aka.ms/aspire/diagnostics/ASPIRE013"
    }
  ]
}