{
  "prefix": "BL",
  "repo": "aspnetcore",
  "description": "Blazor component diagnostics",
  "generated_at": "2026-02-05T02:14:05.829598Z",
  "diagnostics": [
    {
      "id": "BL0001",
      "category": "Analyzer",
      "url": "https://raw.githubusercontent.com/dotnet/AspNetCore.Docs/main/aspnetcore/diagnostics/bl0001.md",
      "error_url": "https://learn.microsoft.com/aspnet/core/diagnostics/bl0001"
    },
    {
      "id": "BL0002",
      "category": "Analyzer",
      "url": "https://raw.githubusercontent.com/dotnet/AspNetCore.Docs/main/aspnetcore/diagnostics/bl0002.md",
      "error_url": "https://learn.microsoft.com/aspnet/core/diagnostics/bl0002"
    },
    {
      "id": "BL0003",
      "category": "Analyzer",
      "url": "https://raw.githubusercontent.com/dotnet/AspNetCore.Docs/main/aspnetcore/diagnostics/bl0003.md",
      "error_url": "https://learn.microsoft.com/aspnet/core/diagnostics/bl0003"
    },
    {
      "id": "BL0004",
      "category": "Analyzer",
      "url": "https://raw.githubusercontent.com/dotnet/AspNetCore.Docs/main/aspnetcore/diagnostics/bl0004.md",
      "error_url": "https://learn.microsoft.com/aspnet/core/diagnostics/bl0004"
    },
    {
      "id": "BL0005",
      "category": "Analyzer",
      "url": "https://raw.githubusercontent.com/dotnet/AspNetCore.Docs/main/aspnetcore/diagnostics/bl0005.md",
      "error_url": "https://learn.microsoft.com/aspnet/core/diagnostics/bl0005"
    },
    {
      "id": "BL0006",
      "category": "Analyzer",
      "url": "https://raw.githubusercontent.com/dotnet/AspNetCore.Docs/main/aspnetcore/diagnostics/bl0006.md",
      "error_url": "https://learn.microsoft.com/aspnet/core/diagnostics/bl0006"
    },
    {
      "id": "BL0007",
      "category": "Analyzer",
      "url": "https://raw.githubusercontent.com/dotnet/AspNetCore.Docs/main/aspnetcore/diagnostics/bl0007.md",
      "error_url": "https://learn.microsoft.com/aspnet/core/diagnostics/bl0007"
    },
    {
      "id": "BL0008",
      "category": "Analyzer",
      "url": "https://raw.githubusercontent.com/dotnet/AspNetCore.Docs/main/aspnetcore/diagnostics/bl0008.md",
      "error_url": "https://learn.microsoft.com/aspnet/core/diagnostics/bl0008"
    },
    {
      "id": "BL0009",
      "category": "Analyzer",
      "url": "https://raw.githubusercontent.com/dotnet/AspNetCore.Docs/main/aspnetcore/diagnostics/bl0009.md",
      "error_url": "https://learn.microsoft.com/aspnet/core/diagnostics/bl0009"
    },
    {
      "id": "BL0010",
      "category": "Analyzer",
      "url": "https://raw.githubusercontent.com/dotnet/AspNetCore.Docs/main/aspnetcore/diagnostics/bl0010.md",
      "error_url": "https://learn.microsoft.com/aspnet/core/diagnostics/bl0010"
    }
  ]
}