{
  "prefix": "MVC",
  "repo": "aspnetcore",
  "description": "MVC analyzers",
  "generated_at": "2026-02-05T01:53:21.0733703Z",
  "diagnostics": [
    {
      "id": "MVC1000",
      "category": "Analyzer",
      "help_url": "https://learn.microsoft.com/aspnet/core/diagnostics/mvc1000"
    },
    {
      "id": "MVC1001",
      "category": "Analyzer",
      "help_url": "https://learn.microsoft.com/aspnet/core/diagnostics/mvc1001"
    },
    {
      "id": "MVC1002",
      "category": "Analyzer",
      "help_url": "https://learn.microsoft.com/aspnet/core/diagnostics/mvc1002"
    },
    {
      "id": "MVC1003",
      "category": "Analyzer",
      "help_url": "https://learn.microsoft.com/aspnet/core/diagnostics/mvc1003"
    },
    {
      "id": "MVC1004",
      "category": "Analyzer",
      "help_url": "https://learn.microsoft.com/aspnet/core/diagnostics/mvc1004"
    },
    {
      "id": "MVC1006",
      "category": "Analyzer",
      "help_url": "https://learn.microsoft.com/aspnet/core/diagnostics/mvc1006"
    }
  ]
}